{"lastUsed":1543192678436,"path":"D:\/application\/java\/eclipseworkspace","projectCount":36,"recentFiles":[{"path":"\/web\/src\/main\/java\/com\/htrfid\/financeapp\/service","parentWorkspace":"D:\/application\/java\/eclipseworkspace","name":"FaSubsidiaryLedgerService.java"},{"path":"\/doraemon-service-finance\/src\/main\/java\/com\/htrfid\/finance\/dao","parentWorkspace":"D:\/application\/java\/eclipseworkspace","name":"FinanceFaCardDao.java"},{"path":"\/doraemon-service-sysmanager\/src\/main\/resources","parentWorkspace":"D:\/application\/java\/eclipseworkspace","name":"application-test.properties"},{"path":"\/web\/src\/main\/java\/com\/htrfid\/financeapp\/service","parentWorkspace":"D:\/application\/java\/eclipseworkspace","name":"CommonService.java"},{"path":"\/web\/src\/main\/java\/com\/htrfid","parentWorkspace":"D:\/application\/java\/eclipseworkspace","name":"StartWebApplication.java"},{"path":"\/doraemon-service-finance\/src\/main\/resources\/mybatis\/mapper","parentWorkspace":"D:\/application\/java\/eclipseworkspace","name":"FinanceFaCardMapper.xml"},{"path":"\/doraemon-service-sysmanager\/src\/main\/resources","parentWorkspace":"D:\/application\/java\/eclipseworkspace","name":"application-prod.properties"},{"path":"\/web\/src\/main\/java\/com\/htrfid\/financeapp\/service\/impl","parentWorkspace":"D:\/application\/java\/eclipseworkspace","name":"FixedAssetsVoucherServiceImpl.java"},{"path":"\/web\/src\/main\/java\/com\/htrfid\/financeapp\/service\/impl","parentWorkspace":"D:\/application\/java\/eclipseworkspace","name":"FaSubsidiaryLedgerServiceImpl.java"},{"path":"\/doraemon-service-finance\/src\/main\/java\/com\/htrfid\/finance\/service\/impl","parentWorkspace":"D:\/application\/java\/eclipseworkspace","name":"FinanceFaCardServiceImpl.java"},{"path":"\/web\/src\/main\/java\/com\/htrfid\/financeapp\/service","parentWorkspace":"D:\/application\/java\/eclipseworkspace","name":"FixedAssetsVoucherService.java"},{"path":"\/Servers\/Tomcat v8.5 Server at localhost-config","parentWorkspace":"D:\/application\/java\/eclipseworkspace","name":"server.xml","lastModified":1542954464626},{"path":"\/doraemon-service-sysmanager\/src\/main\/resources","parentWorkspace":"D:\/application\/java\/eclipseworkspace","name":"application-dev.properties"},{"path":"\/web\/src\/main\/java\/com\/htrfid\/financeapp\/service\/impl","parentWorkspace":"D:\/application\/java\/eclipseworkspace","name":"CommonServiceImpl.java"},{"path":"\/web\/src\/main\/java\/com\/htrfid\/financeapp\/controller","parentWorkspace":"D:\/application\/java\/eclipseworkspace","name":"FaSubsidiaryLedgerController.java"},{"path":"\/doraemon-service-finance\/src\/main\/java\/com\/htrfid\/finance\/service\/impl","parentWorkspace":"D:\/application\/java\/eclipseworkspace","name":"FaSubsidiaryLedgerServiceImpl.java","lastModified":1543192527159},{"path":"\/Servers\/Tomcat v8.5 Server at localhost-config","parentWorkspace":"D:\/application\/java\/eclipseworkspace","name":"catalina.properties","lastModified":1542954028436}]}